{
  "id": "post-1766550902597-58",
  "caption": "Truly amazing dinner by @theglampingchef. All thanks to our incredibly generous friends and family. We are so blessed to be able to have experiences like these. #kzrockiestart",
  "timestamp": "2017-09-26T03:40:09.000Z",
  "author": "zackgilbert",
  "authorAvatar": "https://avatars.githubusercontent.com/u/432526?v=4",
  "imageUrl": "https://raw.githubusercontent.com/zackgilbert/gitstagram-posts/main/posts/post-1766550902597-58/image.jpg",
  "likes": 0,
  "likedBy": [],
  "comments": [],
  "importedFrom": "instagram"
}